README.md
setup.py
halo_flask/__init__.py
halo_flask/apis.py
halo_flask/base_util.py
halo_flask/cache.py
halo_flask/circuitbreaker.py
halo_flask/classes.py
halo_flask/const.py
halo_flask/context.py
halo_flask/errors.py
halo_flask/events.py
halo_flask/exceptions.py
halo_flask/logs.py
halo_flask/mixin_err_msg.py
halo_flask/models.py
halo_flask/reflect.py
halo_flask/request.py
halo_flask/response.py
halo_flask/saga.py
halo_flask/security.py
halo_flask/settingsx.py
halo_flask/ssm.py
halo_flask/sys_util.py
halo_flask.egg-info/PKG-INFO
halo_flask.egg-info/SOURCES.txt
halo_flask.egg-info/dependency_links.txt
halo_flask.egg-info/top_level.txt
halo_flask/flask/__init__.py
halo_flask/flask/filter.py
halo_flask/flask/mixinx.py
halo_flask/flask/servicex.py
halo_flask/flask/utilx.py
halo_flask/flask/viewsx.py
halo_flask/providers/__init__.py
halo_flask/providers/providers.py
halo_flask/providers/cloud/__init__.py
halo_flask/providers/cloud/aws/__init__.py
halo_flask/providers/onprem/__init__.py
halo_flask/providers/ssm/__init__.py
halo_flask/providers/ssm/aws_ssm.py
halo_flask/providers/ssm/onprem_ssm.py
halo_flask/providers/ssm/onprem_ssm_client.py
halo_flask/schema/saga_schema.json