Metadata-Version: 2.1
Name: halo-flask
Version: 0.15.96
Summary: this is the Halo framework library for Flask
Home-page: https://github.com/yoramk2/halo_flask
Author: yoramk2
Author-email: yoramk2@yahoo.com
License: MIT License
Platform: UNKNOWN
Classifier: Environment :: Console
Classifier: License :: OSI Approved :: Apache Software License
Classifier: Operating System :: OS Independent
Classifier: Programming Language :: Python
Classifier: Programming Language :: Python :: 3.6
Classifier: Framework :: Flask
Classifier: Topic :: Internet :: WWW/HTTP
Classifier: Topic :: Internet :: WWW/HTTP :: Dynamic Content
